imghashpy-0.1.0.dist-info/METADATA
imghashpy-0.1.0.dist-info/WHEEL
imghashpy/__init__.py
imghashpy/__init__.pyi
imghashpy/py.typed
imghashpy/imghashpy.cp38-win_amd64.pyd
imghashpy-0.1.0.dist-info/RECORD
