Metadata-Version: 2.3
Name: imghashpy
Version: 0.1.0
